{
    "ServiceSettings": {
        "ListenAddress": ":8080",
        "MaximumLoginAttempts": 10,
        "SegmentDeveloperKey": "",
        "GoogleDeveloperKey": "",
        "EnableOAuthServiceProvider": false,
        "EnableIncomingWebhooks": false,
        "EnableOutgoingWebhooks": false,
        "EnablePostUsernameOverride": false,
        "EnablePostIconOverride": false,
        "EnableTesting": false,
        "EnableSecurityFixAlert": true
    },
    "TeamSettings": {
        "SiteName": "Mattermost",
        "MaxUsersPerTeam": 50,
        "EnableTeamCreation": true,
        "EnableUserCreation": true,
        "RestrictCreationToDomains": "",
        "RestrictTeamNames": true,
        "EnableTeamListing": false
    },
    "SqlSettings": {
        "DriverName": "postgres",
        "DataSource": "postgres://mattermost:POSTGRES_PASSWORD@db:5432/mattermost?sslmode=disable&connect_timeout=10",
        "DataSourceReplicas": [],
        "MaxIdleConns": 10,
        "MaxOpenConns": 10,
        "Trace": false,
        "AtRestEncryptKey": "ChangeAtRestEncryptKey"
    },
    "LogSettings": {
        "EnableConsole": false,
        "ConsoleLevel": "INFO",
        "EnableFile": true,
        "FileLevel": "INFO",
        "FileFormat": "",
        "FileLocation": ""
    },
    "FileSettings": {
        "DriverName": "local",
        "Directory": "/mattermost/data/",
        "EnablePublicLink": true,
        "PublicLinkSalt": "ChangePublicLinkSalt",
        "ThumbnailWidth": 120,
        "ThumbnailHeight": 100,
        "PreviewWidth": 1024,
        "PreviewHeight": 0,
        "ProfileWidth": 128,
        "ProfileHeight": 128,
        "InitialFont": "luximbi.ttf",
        "AmazonS3AccessKeyId": "",
        "AmazonS3SecretAccessKey": "",
        "AmazonS3Bucket": "",
        "AmazonS3Region": ""
    },
    "EmailSettings": {
        "EnableSignUpWithEmail": true,
        "SendEmailNotifications": false,
        "RequireEmailVerification": false,
        "FeedbackName": "",
        "FeedbackEmail": "",
        "SMTPUsername": "",
        "SMTPPassword": "",
        "SMTPServer": "",
        "SMTPPort": "",
        "ConnectionSecurity": "",
        "InviteSalt": "ChangeInviteSalt",
        "PasswordResetSalt": "ChangePasswordResetSalt",
        "ApplePushServer": "",
        "ApplePushCertPublic": "",
        "ApplePushCertPrivate": ""
    },
    "RateLimitSettings": {
        "EnableRateLimiter": true,
        "PerSec": 10,
        "MemoryStoreSize": 10000,
        "VaryByRemoteAddr": true,
        "VaryByHeader": ""
    },
    "PrivacySettings": {
        "ShowEmailAddress": true,
        "ShowFullName": true
    },
    "GitLabSettings": {
        "Enable": false,
        "Secret": "",
        "Id": "",
        "Scope": "",
        "AuthEndpoint": "",
        "TokenEndpoint": "",
        "UserApiEndpoint": ""
    }
}
